flag_gems/__init__.py
flag_gems/config.py
flag_gems/logging_utils.py
flag_gems/experimental_ops/__init__.py
flag_gems/experimental_ops/relu.py
flag_gems/experimental_ops/rmsnorm.py
flag_gems/experimental_ops/exp_tests/__init__.py
flag_gems/experimental_ops/exp_tests/relu_test.py
flag_gems/experimental_ops/exp_tests/rmsnorm_test.py
flag_gems/fused/__init__.py
flag_gems/fused/apply_repetition_penalties.py
flag_gems/fused/concat_and_cache_mla.py
flag_gems/fused/cross_entropy_loss.py
flag_gems/fused/flash_mla.py
flag_gems/fused/fused_add_rms_norm.py
flag_gems/fused/geglu.py
flag_gems/fused/gelu_and_mul.py
flag_gems/fused/instance_norm.py
flag_gems/fused/moe_align_block_size.py
flag_gems/fused/moe_sum.py
flag_gems/fused/outer.py
flag_gems/fused/reglu.py
flag_gems/fused/reshape_and_cache.py
flag_gems/fused/reshape_and_cache_flash.py
flag_gems/fused/rotary_embedding.py
flag_gems/fused/rwkv_ka_fusion.py
flag_gems/fused/rwkv_mm_sparsity.py
flag_gems/fused/silu_and_mul.py
flag_gems/fused/skip_layernorm.py
flag_gems/fused/topk_softmax.py
flag_gems/fused/weight_norm.py
flag_gems/fused/DSA/bin_topk.py
flag_gems/fused/DSA/indexer_k_tiled.py
flag_gems/fused/DSA/sparse_mla.py
flag_gems/modules/__init__.py
flag_gems/modules/activation.py
flag_gems/modules/normalization.py
flag_gems/modules/rotary_embedding.py
flag_gems/ops/__init__.py
flag_gems/ops/abs.py
flag_gems/ops/add.py
flag_gems/ops/addcdiv.py
flag_gems/ops/addcmul.py
flag_gems/ops/addmm.py
flag_gems/ops/addmv.py
flag_gems/ops/addr.py
flag_gems/ops/all.py
flag_gems/ops/amax.py
flag_gems/ops/angle.py
flag_gems/ops/any.py
flag_gems/ops/arange.py
flag_gems/ops/argmax.py
flag_gems/ops/argmin.py
flag_gems/ops/atan.py
flag_gems/ops/attention.py
flag_gems/ops/avg_pool2d.py
flag_gems/ops/baddbmm.py
flag_gems/ops/batch_norm.py
flag_gems/ops/bitwise_and.py
flag_gems/ops/bitwise_left_shift.py
flag_gems/ops/bitwise_not.py
flag_gems/ops/bitwise_or.py
flag_gems/ops/bitwise_right_shift.py
flag_gems/ops/bmm.py
flag_gems/ops/cat.py
flag_gems-4.2.0.dist-info/LICENSE
flag_gems-4.2.0.dist-info/METADATA
flag_gems-4.2.0.dist-info/WHEEL
flag_gems-4.2.0.dist-info/top_level.txt
flag_gems-4.2.0.dist-info/RECORD
